django_cloud_tasks/__init__.py
django_cloud_tasks/apps.py
django_cloud_tasks/base.py
django_cloud_tasks/connection.py
django_cloud_tasks/constants.py
django_cloud_tasks/decorators.py
django_cloud_tasks/registries.py
django_cloud_tasks/urls.py
django_cloud_tasks/views.py
django_cloud_tasks-0.0.4.dist-info/METADATA
django_cloud_tasks-0.0.4.dist-info/RECORD
django_cloud_tasks-0.0.4.dist-info/WHEEL
django_cloud_tasks-0.0.4.dist-info/top_level.txt
