Metadata-Version: 2.1
Name: django-cloud-tasks
Version: 0.0.4
Summary: Google Cloud Tasks integration for Django
Home-page: https://github.com/GeorgeLubaretsi/django-cloud-tasks
Author: GeorgeLubaretsi
Author-email: UNKNOWN
License: MIT
Keywords: django cloudtasks cloud tasks
Platform: UNKNOWN
Classifier: Framework :: Django
Classifier: Framework :: Django :: 1.11
Classifier: Framework :: Django :: 2.0
Classifier: Intended Audience :: Developers
Classifier: License :: OSI Approved :: BSD License
Classifier: Natural Language :: English
Classifier: Programming Language :: Python :: 3
Classifier: Programming Language :: Python :: 3.4
Classifier: Programming Language :: Python :: 3.5
Classifier: Programming Language :: Python :: 3.6
Requires-Dist: google-api-python-client (>=1.6.4)
